[
    {
        "id": 1,
        "owner_id": "695d2f34db4b2",
        "title": "calculator",
        "description": "very good working",
        "category": "student-essentials",
        "price_per_day": "50.00",
        "security_deposit": "0.00",
        "condition_status": "good",
        "availability_status": "available",
        "active_until": null,
        "listing_duration": null,
        "location": "kanjirappally",
        "city": null,
        "state": null,
        "pincode": null,
        "images": [
            "695d3900f253b_c2.webp",
            "695d3900f3b46_c1.jpg"
        ],
        "is_active": 1,
        "views_count": 0,
        "created_at": "2026-01-06 17:32:01",
        "updated_at": "2026-01-30 00:17:53",
        "handover_methods": null,
        "admin_status": "approved",
        "price": "50.00",
        "address": "kanjirappally",
        "status": "Active"
    },
    {
        "id": 7,
        "owner_id": "695a9a1b6d290",
        "title": "Raincoat",
        "description": "good",
        "category": "outdoor-gear",
        "price_per_day": "150.00",
        "security_deposit": "0.00",
        "condition_status": "good",
        "availability_status": "available",
        "active_until": null,
        "listing_duration": null,
        "location": "kanjirappally",
        "city": null,
        "state": null,
        "pincode": null,
        "images": [
            "696338ce0ee29_r2.jpg",
            "696338ce12cc3_r1.jpg"
        ],
        "is_active": 1,
        "views_count": 0,
        "created_at": "2026-01-11 06:44:46",
        "updated_at": "2026-01-30 00:17:53",
        "handover_methods": null,
        "admin_status": "approved",
        "price": "150.00",
        "address": "kanjirappally",
        "status": "Active"
    },
    {
        "id": 8,
        "owner_id": "6948d636dab97",
        "title": "umberlla",
        "description": "good",
        "category": "outdoor-gear",
        "price_per_day": "150.00",
        "security_deposit": "0.00",
        "condition_status": "good",
        "availability_status": "available",
        "active_until": null,
        "listing_duration": null,
        "location": "kanjirappally",
        "city": null,
        "state": null,
        "pincode": null,
        "images": [
            "6964ba6b4fc07_u1.avif"
        ],
        "is_active": 1,
        "views_count": 0,
        "created_at": "2026-01-12 10:10:03",
        "updated_at": "2026-01-30 00:17:53",
        "handover_methods": null,
        "admin_status": "approved",
        "price": "150.00",
        "address": "kanjirappally",
        "status": "Active"
    },
    {
        "id": 15,
        "owner_id": "695a9a1b6d290",
        "title": "Raincoat",
        "description": "good",
        "category": "outdoor-gear",
        "price_per_day": "150.00",
        "security_deposit": "0.00",
        "condition_status": "good",
        "availability_status": "available",
        "active_until": null,
        "listing_duration": null,
        "location": "kanjirappally",
        "city": null,
        "state": null,
        "pincode": null,
        "images": [
            "696338ce0ee29_r2.jpg",
            "696338ce12cc3_r1.jpg"
        ],
        "is_active": 1,
        "views_count": 0,
        "created_at": "2026-01-11 06:44:46",
        "updated_at": "2026-01-30 00:17:53",
        "handover_methods": null,
        "admin_status": "approved",
        "price": "150.00",
        "address": "kanjirappally",
        "status": "Active"
    },
    {
        "id": 16,
        "owner_id": "6948d636dab97",
        "title": "umberlla",
        "description": "good",
        "category": "outdoor-gear",
        "price_per_day": "150.00",
        "security_deposit": "0.00",
        "condition_status": "good",
        "availability_status": "available",
        "active_until": null,
        "listing_duration": null,
        "location": "kanjirappally",
        "city": null,
        "state": null,
        "pincode": null,
        "images": [
            "6964ba6b4fc07_u1.avif"
        ],
        "is_active": 1,
        "views_count": 0,
        "created_at": "2026-01-12 10:10:03",
        "updated_at": "2026-01-30 00:17:53",
        "handover_methods": null,
        "admin_status": "approved",
        "price": "150.00",
        "address": "kanjirappally",
        "status": "Active"
    },
    {
        "id": 23,
        "owner_id": "695a9a1b6d290",
        "title": "Raincoat",
        "description": "good",
        "category": "outdoor-gear",
        "price_per_day": "150.00",
        "security_deposit": "0.00",
        "condition_status": "good",
        "availability_status": "available",
        "active_until": null,
        "listing_duration": null,
        "location": "kanjirappally",
        "city": null,
        "state": null,
        "pincode": null,
        "images": [
            "696338ce0ee29_r2.jpg",
            "696338ce12cc3_r1.jpg"
        ],
        "is_active": 1,
        "views_count": 0,
        "created_at": "2026-01-11 06:44:46",
        "updated_at": "2026-01-30 00:17:53",
        "handover_methods": null,
        "admin_status": "approved",
        "price": "150.00",
        "address": "kanjirappally",
        "status": "Active"
    },
    {
        "id": 24,
        "owner_id": "6948d636dab97",
        "title": "umberlla",
        "description": "good",
        "category": "outdoor-gear",
        "price_per_day": "150.00",
        "security_deposit": "0.00",
        "condition_status": "good",
        "availability_status": "available",
        "active_until": null,
        "listing_duration": null,
        "location": "kanjirappally",
        "city": null,
        "state": null,
        "pincode": null,
        "images": [
            "6964ba6b4fc07_u1.avif"
        ],
        "is_active": 1,
        "views_count": 0,
        "created_at": "2026-01-12 10:10:03",
        "updated_at": "2026-01-30 00:17:53",
        "handover_methods": null,
        "admin_status": "approved",
        "price": "150.00",
        "address": "kanjirappally",
        "status": "Active"
    },
    {
        "id": 25,
        "owner_id": "6948d636dab97",
        "title": "Test Item 1768839023",
        "description": "This is a test item to verify database insertion.",
        "category": "electronics",
        "price_per_day": "100.00",
        "security_deposit": "50.00",
        "condition_status": "good",
        "availability_status": "available",
        "active_until": null,
        "listing_duration": null,
        "location": "Test Location",
        "city": null,
        "state": null,
        "pincode": null,
        "images": [
            "test_image.jpg"
        ],
        "is_active": 1,
        "views_count": 0,
        "created_at": "2026-01-19 21:40:23",
        "updated_at": "2026-01-19 21:59:39",
        "handover_methods": "[\"pickup\"]",
        "admin_status": "approved",
        "price": "100.00",
        "address": "Test Location",
        "status": "Active"
    },
    {
        "id": 26,
        "owner_id": "696e57fc247b3",
        "title": "Iron box",
        "description": "Efficient and easy-to-use iron box suitable for daily clothes ironing. Provides even heat distribution for smooth and wrinkle-free results.",
        "category": "home-essentials",
        "price_per_day": "200.00",
        "security_deposit": "0.00",
        "condition_status": "good",
        "availability_status": "available",
        "active_until": null,
        "listing_duration": null,
        "location": "Idukki",
        "city": null,
        "state": null,
        "pincode": null,
        "images": [
            "696e5aa6f0057_How to Clean a Front-Loading Washing Machine With These Easy Steps.jpg",
            "696e5aa6f354f_download (2).jpg"
        ],
        "is_active": 1,
        "views_count": 0,
        "created_at": "2026-01-19 21:54:07",
        "updated_at": "2026-01-19 21:55:04",
        "handover_methods": "[\"pickup\"]",
        "admin_status": "approved",
        "price": "200.00",
        "address": "Idukki",
        "status": "Active"
    },
    {
        "id": 27,
        "owner_id": "696e57fc247b3",
        "title": "Rain coat",
        "description": "Stay dry during sudden rains with our high-quality raincoat for rent. Designed for comfort and full coverage, this raincoat is lightweight, waterproof, and easy to carry\u2014perfect for daily travel, bike rides, and outdoor use.",
        "category": "outdoor-gear",
        "price_per_day": "200.00",
        "security_deposit": "0.00",
        "condition_status": "good",
        "availability_status": "available",
        "active_until": "2026-02-27 17:20:22",
        "listing_duration": 30,
        "location": "Mundakkayam",
        "city": null,
        "state": null,
        "pincode": null,
        "images": [
            "696f074bae303_JOULES Portwell Yellow Waterproof Raincoat With Hood and Adjustable Waist 6 Womens.jpg",
            "696f074bb2dbe_Yellow Raincoat.jpg"
        ],
        "is_active": 1,
        "views_count": 0,
        "created_at": "2026-01-20 10:10:43",
        "updated_at": "2026-01-28 21:50:22",
        "handover_methods": "[\"pickup\"]",
        "admin_status": "approved",
        "price": "200.00",
        "address": "Mundakkayam",
        "status": "Active"
    },
    {
        "id": 28,
        "owner_id": "697ad695ad641",
        "title": "Dumbbells",
        "description": "Durable dumbbells for rent, suitable for home workouts and strength training. Clean, well-maintained, and available at affordable rental rates.",
        "category": "fitness",
        "price_per_day": "80.00",
        "security_deposit": "0.00",
        "condition_status": "good",
        "availability_status": "available",
        "active_until": "2026-02-28 18:25:08",
        "listing_duration": 30,
        "location": "Kumily",
        "city": null,
        "state": null,
        "pincode": null,
        "images": [
            "697b95474b584_single-dumbbell-rests-wet-floor-gym.jpg",
            "697b95474deea_metal-dumbbell-wooden-surface-sunlight-shines-through-window.jpg"
        ],
        "is_active": 1,
        "views_count": 0,
        "created_at": "2026-01-29 22:43:43",
        "updated_at": "2026-01-29 22:55:08",
        "handover_methods": "[\"pickup\"]",
        "admin_status": "approved",
        "price": "80.00",
        "address": "Kumily",
        "status": "Active"
    },
    {
        "id": 29,
        "owner_id": "697ad695ad641",
        "title": "Almirah",
        "description": "Strong and spacious almirah for rent, suitable for homes and hostels. Clean, durable, and easy to use.",
        "category": "furniture",
        "price_per_day": "600.00",
        "security_deposit": "0.00",
        "condition_status": "good",
        "availability_status": "available",
        "active_until": "2026-03-30 18:25:06",
        "listing_duration": 60,
        "location": "Erumeli",
        "city": null,
        "state": null,
        "pincode": null,
        "images": [
            "697b97cc8b9bf_TEAK WARDROBE.jpg",
            "697b97cc8d304_download (3).jpg"
        ],
        "is_active": 1,
        "views_count": 0,
        "created_at": "2026-01-29 22:54:28",
        "updated_at": "2026-01-29 22:55:06",
        "handover_methods": "[\"delivery\"]",
        "admin_status": "approved",
        "price": "600.00",
        "address": "Erumeli",
        "status": "Active"
    },
    {
        "id": 30,
        "owner_id": "695a8dc1e017b",
        "title": "Hanging Swing ",
        "description": "The swing chair is well-maintained, securely assembled, and cleaned before every rental. It is suitable for daily use and ideal for short-term as well as long-term rentals.",
        "category": "furniture",
        "price_per_day": "650.00",
        "security_deposit": "0.00",
        "condition_status": "good",
        "availability_status": "available",
        "active_until": "2026-02-28 18:52:44",
        "listing_duration": 30,
        "location": "Kattappana",
        "city": null,
        "state": null,
        "pincode": null,
        "images": [
            "697b99c1157b0_download (4).jpg",
            "697b99c117026_Elevate your living space with a distinctive touch of elegance by incorporating a beautiful heritage swing into your room decor_.jpg"
        ],
        "is_active": 1,
        "views_count": 0,
        "created_at": "2026-01-29 23:02:49",
        "updated_at": "2026-01-29 23:22:44",
        "handover_methods": "[\"delivery\"]",
        "admin_status": "approved",
        "price": "650.00",
        "address": "Kattappana",
        "status": "Active"
    },
    {
        "id": 31,
        "owner_id": "696e57fc247b3",
        "title": "Dining chairs",
        "description": "Comfortable and sturdy dining chairs available for rent, suitable for homes, hostels, and temporary setups. Well-maintained and easy to move, ideal for daily dining use.",
        "category": "furniture",
        "price_per_day": "250.00",
        "security_deposit": "0.00",
        "condition_status": "good",
        "availability_status": "available",
        "active_until": "2026-02-28 18:41:17",
        "listing_duration": 30,
        "location": "Nedumkandam",
        "city": null,
        "state": null,
        "pincode": null,
        "images": [
            "697b9b9def3ac_download (5).jpg",
            "697b9b9df1d54_Chaussures en cuir pour hommes, baskets de marque de luxe anglaises, tendance, d\u00e9contract\u00e9es, respirantes, loisirs, 2022.jpg"
        ],
        "is_active": 1,
        "views_count": 0,
        "created_at": "2026-01-29 23:10:46",
        "updated_at": "2026-01-29 23:11:17",
        "handover_methods": "[\"delivery\"]",
        "admin_status": "approved",
        "price": "250.00",
        "address": "Nedumkandam",
        "status": "Active"
    },
    {
        "id": "item_697bb3cba6ded",
        "user_id": "697bb26600c09",
        "owner_name": "Aninta Johny",
        "title": "Desk lamp",
        "category": "student-essentials",
        "price": "50",
        "security_deposit": "",
        "handover_methods": [
            "pickup"
        ],
        "description": "Brighten your workspace with our sleek desk lamp, available for rent. Adjustable, energy-efficient, and perfect for study or office use",
        "address": "pala",
        "images": [
            "697bb3cba343d_desk_lamp.jpg",
            "697bb3cba4d20_Kandem \u2013 Mod_ 967.jpg"
        ],
        "created_at": "2026-01-29 20:23:55",
        "status": "Pending Approval"
    },
    {
        "id": "item_697bb5bee5da0",
        "user_id": "697bb26600c09",
        "owner_name": "Aninta Johny",
        "title": "Whiteboard",
        "category": "student-essentials",
        "price": "100",
        "security_deposit": "",
        "handover_methods": [
            "pickup"
        ],
        "description": "Make your ideas visible with our portable whiteboard. Perfect for meetings, classes, and brainstorming sessions.",
        "address": "Kattappana",
        "images": [
            "697bb5bee14fa_Luxor Mobile Dry Erase Double-Sided Magnetic Whiteboard with Aluminum Frame and Stand - 96_W x 40_H.jpg",
            "697bb5bee2b41_VIZ-PRO Double-Sided Magnetic Mobile Whiteboard, 48 x 36 Inches, Steel Stand.jpg"
        ],
        "created_at": "2026-01-29 20:32:14",
        "status": "Pending Approval"
    },
    {
        "id": "item_697bb6b53f3e2",
        "user_id": "697bb26600c09",
        "owner_name": "Aninta Johny",
        "title": "Geometry Box",
        "category": "student-essentials",
        "price": "30",
        "security_deposit": "",
        "handover_methods": [
            "pickup"
        ],
        "description": "Get all your measuring tools in one! Geometry box available for rent perfect for students and drawing tasks",
        "address": "kattappana",
        "images": [
            "697bb6b53ab31_download (6).jpg",
            "697bb6b53bc96_Small drafting set.jpg"
        ],
        "created_at": "2026-01-29 20:36:21",
        "status": "Pending Approval"
    },
    {
        "id": "item_697bb891d29d3",
        "user_id": "697bb26600c09",
        "owner_name": "Aninta Johny",
        "title": "Foldable camping chairs",
        "category": "outdoor-gear",
        "price": "150",
        "security_deposit": "",
        "handover_methods": [
            "pickup"
        ],
        "description": "Lightweight foldable camping chair in great condition. Comfortable seating for camping, beach, or travel breaks",
        "address": "Kattappana",
        "images": [
            "697bb891ce6e2_download (7).jpg",
            "697bb891d1793_LEADALLWAY Folding Camping Chair Oversized Collapsible Camp Chair with Cup Holder and Removable Storage Bag, Heavy Duty Support 350 LBS, Portable Lawn.jpg"
        ],
        "created_at": "2026-01-29 20:44:17",
        "status": "Pending Approval"
    },
    {
        "id": "item_697bb928f304f",
        "user_id": "697bb26600c09",
        "owner_name": "Aninta Johny",
        "title": "Tents",
        "category": "outdoor-gear",
        "price": "300",
        "security_deposit": "",
        "handover_methods": [
            "pickup"
        ],
        "description": "Tent in good condition. Clean, waterproof, and well-maintained. Suitable for camping and outdoor stays",
        "address": "Kattappana",
        "images": [
            "697bb928f165c_download (8).jpg",
            "697bb928f2761_Outdoor 2-4 Persons Camping Tent Double Layer Waterproof Windproof Anti-Uv Sunshade Canopy.gif"
        ],
        "created_at": "2026-01-29 20:46:48",
        "status": "Pending Approval"
    },
    {
        "id": "item_697bba1b29748",
        "user_id": "696e57fc247b3",
        "owner_name": "Rincy Joseph",
        "title": "Camping stove & cookware",
        "category": "outdoor-gear",
        "price": "180",
        "security_deposit": "",
        "handover_methods": [
            "pickup"
        ],
        "description": "Camping stove and cookware set in good condition. Clean, fully functional, and safe for outdoor cooking",
        "address": "Kumily",
        "images": [
            "697bba1b230b6_Cookware Set,Person Pot Set Pot Set With Dishes Utensils 5-8 Set Portable Portable Dishes Kettle Pan Picnic Set With Kettle 5-8 Person Pot Cookware Set Portable.jpg",
            "697bba1b263e8_Camping cookware.jpg"
        ],
        "created_at": "2026-01-29 20:50:51",
        "status": "Pending Approval"
    },
    {
        "id": "item_697bbaf6b06d0",
        "user_id": "696e57fc247b3",
        "owner_name": "Rincy Joseph",
        "title": "Microwave ovens",
        "category": "home-essentials",
        "price": "300",
        "security_deposit": "",
        "handover_methods": [
            "pickup"
        ],
        "description": "Microwave oven in good condition. Clean, fully functional, and suitable for daily heating and cooking needs.",
        "address": "Kumily",
        "images": [
            "697bbaf6acf8a_Micro-ondas 32 Litros Panasonic ST66LBRUN Preto 110V - Micro-ondas - Magazine Luiza.jpg",
            "697bbaf6aec32_Top microwave oven.jpg"
        ],
        "created_at": "2026-01-29 20:54:30",
        "status": "Pending Approval"
    },
    {
        "id": "item_697bbb5e67f92",
        "user_id": "696e57fc247b3",
        "owner_name": "Rincy Joseph",
        "title": "Electric kettles",
        "category": "home-essentials",
        "price": "100",
        "security_deposit": "",
        "handover_methods": [
            "pickup"
        ],
        "description": "Electric kettle in good condition. Clean, heats quickly, and fully functional",
        "address": "Kumily",
        "images": [
            "697bbb5e63f5f_Cord-Free Serving.jpg",
            "697bbb5e6628f_download (9).jpg"
        ],
        "created_at": "2026-01-29 20:56:14",
        "status": "Pending Approval"
    },
    {
        "id": "item_697bbc993841f",
        "user_id": "696e57fc247b3",
        "owner_name": "Rincy Joseph",
        "title": "Yoga mats",
        "category": "fitness",
        "price": "50",
        "security_deposit": "",
        "handover_methods": [
            "pickup"
        ],
        "description": "Yoga mat in good condition. Clean, non-slip, and comfortable for daily workouts",
        "address": "Kumily",
        "images": [
            "697bbc9930694_PROlite Yoga Mat - Black Sage.jpg",
            "697bbc993480d_HUSL Esterilla Yoga Antideslizante, Alfombrilla Deportiva para Fitness Grosor Extra, Yoga Colchoneta Antideslizante para Yoga, Pilates, Deporte, Gimnasia, Fitness, meditaci\u00f3n_ 183cm x 61cm (P\u00farpura).jpg"
        ],
        "created_at": "2026-01-29 21:01:29",
        "status": "Pending Approval"
    },
    {
        "id": "item_697bbd1294961",
        "user_id": "696e57fc247b3",
        "owner_name": "Rincy Joseph",
        "title": "Treadmills",
        "category": "fitness",
        "price": "800",
        "security_deposit": "",
        "handover_methods": [
            "delivery"
        ],
        "description": "Treadmill in good condition. Smooth running belt, fully functional, and well-maintained",
        "address": "Kumily",
        "images": [
            "697bbd1290c89_Tapis de course Hammer Life Runner LR20.jpg",
            "697bbd1292165_These 9 Budget Treadmills Work Just as Well as $1,000+ Models.jpg"
        ],
        "created_at": "2026-01-29 21:03:30",
        "status": "Pending Approval"
    },
    {
        "id": "item_697bbe2b621a1",
        "user_id": "695a8dc1e017b",
        "owner_name": "Agnus Sabu",
        "title": "Skipping ropes",
        "category": "fitness",
        "price": "25",
        "security_deposit": "",
        "handover_methods": [
            "pickup"
        ],
        "description": "Well-maintained skipping rope in proper working condition with comfortable handles. Suitable for fitness training",
        "address": "pala",
        "images": [
            "697bbe2b5c702_download (10).jpg",
            "697bbe2b5fdc8_Fitness Rope Skipping Steel Wire Rope Weight Loss Equipment - Green.jpg"
        ],
        "created_at": "2026-01-29 21:08:11",
        "status": "Pending Approval"
    },
    {
        "id": "item_697bbefe08c1c",
        "user_id": "695a8dc1e017b",
        "owner_name": "Agnus Sabu",
        "title": "Stretching straps",
        "category": "fitness",
        "price": "30",
        "security_deposit": "",
        "handover_methods": [
            "pickup"
        ],
        "description": "Stretching strap in good working condition. Clean, strong, and flexible\u2014perfect for stretching and yoga exercises.",
        "address": "pala",
        "images": [
            "697bbefdc6367_Yoga straps.jpg",
            "697bbefde630e_Freely Yoga Training Strap _ Academy.jpg"
        ],
        "created_at": "2026-01-29 21:11:42",
        "status": "Pending Approval"
    },
    {
        "id": "item_697bbfed1bfa4",
        "user_id": "695a8dc1e017b",
        "owner_name": "Agnus Sabu",
        "title": "Water pumps",
        "category": "agriculture",
        "price": "400",
        "security_deposit": "",
        "handover_methods": [
            "pickup"
        ],
        "description": "Water pump in good working condition. Clean, fully functional, and efficient for irrigation and farm use",
        "address": "pala",
        "images": [
            "697bbfed132d6_{productName}.jpg",
            "697bbfed19fdb_download (11).jpg"
        ],
        "created_at": "2026-01-29 21:15:41",
        "status": "Pending Approval"
    },
    {
        "id": "item_697bc09a3658b",
        "user_id": "695a8dc1e017b",
        "owner_name": "Agnus Sabu",
        "title": "Crop sprayer",
        "category": "agriculture",
        "price": "300",
        "security_deposit": "",
        "handover_methods": [
            "pickup"
        ],
        "description": "Crop sprayer in good working condition. Clean, fully functional, and efficient for spraying pesticides, herbicides, and fertilizers",
        "address": "pala",
        "images": [
            "697bc09a2d206_Jacto PJB-8c Backpack Sprayer, Blue.jpg",
            "697bc09a2f8d6_Battery-Powered Shoulder-Carry Sprayer.jpg"
        ],
        "created_at": "2026-01-29 21:18:34",
        "status": "Pending Approval"
    },
    {
        "id": "item_697bc153170ff",
        "user_id": "697ad695ad641",
        "owner_name": "Krishnaveni",
        "title": "Tillers",
        "category": "agriculture",
        "price": "700",
        "security_deposit": "",
        "handover_methods": [
            "delivery"
        ],
        "description": "Tiller in good working condition. Clean, fully functional, and efficient for soil preparation",
        "address": "kanjirappally",
        "images": [
            "697bc152b9dbf_MAXLANDER Cordless Tiller Cultivator Review.jpg",
            "697bc152da413_Vevor Tiller Cultivator 43CC 2-Stroke Engine with 4 Adjustable Steel T.jpg"
        ],
        "created_at": "2026-01-29 21:21:39",
        "status": "Pending Approval"
    },
    {
        "id": "item_697bc21b09bb3",
        "user_id": "697ad695ad641",
        "owner_name": "Krishnaveni",
        "title": "Wheelchairs",
        "category": "medical",
        "price": "350",
        "security_deposit": "",
        "handover_methods": [
            "delivery"
        ],
        "description": "Well-maintained manual wheelchair in proper working condition. Reliable and safe for patient use in hospitals or home settings",
        "address": "kanjirappally",
        "images": [
            "697bc21a6d619_Logotipo.jpg",
            "697bc21ac3d70_#Excel-G5-Modular-Self-Propelled-Lightweight-Wheelchair.jpg"
        ],
        "created_at": "2026-01-29 21:24:59",
        "status": "Pending Approval"
    },
    {
        "id": "item_697bc31caf39b",
        "user_id": "697ad695ad641",
        "owner_name": "Krishnaveni",
        "title": "Blood pressure monitors",
        "category": "medical",
        "price": "120",
        "security_deposit": "",
        "handover_methods": [
            "pickup"
        ],
        "description": "Blood pressure monitor in good working condition. Clean, accurate, and fully functional for home or clinical use",
        "address": "kanjirappally",
        "images": [
            "697bc31bed799_download (13).jpg",
            "697bc31c2c0fd_download (12).jpg",
            "697bc31c88192_Electronic Automatic Upper Arm Blood Pressure Monitor Electric Digital Bp Machine Sphygmomanometer With English Voice.jpg"
        ],
        "created_at": "2026-01-29 21:29:16",
        "status": "Pending Approval"
    },
    {
        "id": "item_697bc3c779bd5",
        "user_id": "697ad695ad641",
        "owner_name": "Krishnaveni",
        "title": "walkers",
        "category": "medical",
        "price": "170",
        "security_deposit": "",
        "handover_methods": [
            "pickup"
        ],
        "description": "Well-maintained walker in proper working condition. Reliable, safe, and ready for home or clinical use",
        "address": "kanjirappally",
        "images": [
            "697bc3c7725ee_Economy Manual Folding Manual Lightweight Standing Frame Aluminum Folding Walkers For Elderly People.jpg",
            "697bc3c775f3f_Single Release Walker.jpg"
        ],
        "created_at": "2026-01-29 21:32:07",
        "status": "Pending Approval"
    },
    {
        "id": "item_697c37ac33eed",
        "user_id": "697c3680ea72f",
        "owner_name": "Jinonse Roy",
        "title": "Typewriter",
        "category": "vintage",
        "price": "350",
        "security_deposit": "",
        "handover_methods": [
            "pickup"
        ],
        "description": "Well-preserved vintage typewriter with classic design. Ideal for display, shoots, and period themes",
        "address": "Erumeli",
        "images": [
            "697c37ac2d2aa_@cemeterydoggs.jpg",
            "697c37ac31166_download (14).jpg"
        ],
        "created_at": "2026-01-30 05:46:36",
        "status": "Pending Approval"
    },
    {
        "id": "item_697c393730baf",
        "user_id": "697c3680ea72f",
        "owner_name": "Jinonse Roy",
        "title": "Old sewing machines",
        "category": "vintage",
        "price": "300",
        "security_deposit": "",
        "handover_methods": [
            "delivery"
        ],
        "description": "Vintage sewing machine in good working condition, suitable for regular use",
        "address": "Erumeli",
        "images": [
            "697c39372bf5d_\ud83e\udea1.jpg",
            "697c39372da36_download (15).jpg"
        ],
        "created_at": "2026-01-30 05:53:11",
        "status": "Pending Approval"
    },
    {
        "id": "item_697c4efd89e60",
        "user_id": "697c3680ea72f",
        "owner_name": "Jinonse Roy",
        "title": "Table fan",
        "category": "home-essentials",
        "price": "120",
        "security_deposit": "",
        "handover_methods": [
            "pickup"
        ],
        "description": "Table fan in good working condition. Clean and efficient for daily use.",
        "address": "Erumeli",
        "images": [
            "697c4efd2b300_Fan.jpg",
            "697c4efd3fb36_download (16).jpg",
            "697c4efd5c230_This item is unavailable - Etsy.jpg"
        ],
        "created_at": "2026-01-30 07:26:05",
        "status": "Pending Approval"
    },
    {
        "id": "item_697e2b2c9d24f",
        "user_id": "697c3680ea72f",
        "owner_name": "Jinonse Roy",
        "title": "Scientific calculator",
        "category": "student-essentials",
        "price": "40",
        "security_deposit": "",
        "handover_methods": [
            "pickup"
        ],
        "description": "Fully functional scientific calculator in good condition for academic use.",
        "address": "Erumeli",
        "images": [
            "697e2b2c7bca6_Scientific Calculator with 2-line display, best for Engineering Calculations with 240 plus function.jpg",
            "697e2b2c87cac_Scientific calculator 240 functions _ Suitable for School Students, Engineer, Teachers, and Business.jpg"
        ],
        "created_at": "2026-01-31 17:17:48",
        "status": "Pending Approval"
    },
    {
        "id": "item_697e2c8a4e729",
        "user_id": "697c3680ea72f",
        "owner_name": "Jinonse Roy",
        "title": "Helmet",
        "category": "outdoor-gear",
        "price": "80",
        "security_deposit": "",
        "handover_methods": [
            "pickup"
        ],
        "description": "Helmet in good condition, clean and safe to use.",
        "address": "Erumeli",
        "images": [
            "697e2c8a4274f_Helmet Biltwell Gringo S Agave Blue Gloss  - X-Large.jpg",
            "697e2c8a4b7a2_Casco Integral JD One Frozen Blue - John Doe  - SMALL.jpg"
        ],
        "created_at": "2026-01-31 17:23:38",
        "status": "Pending Approval"
    },
    {
        "id": "item_697e2df6277c2",
        "user_id": "697e2d046713b",
        "owner_name": "Benta Biju",
        "title": "Extension board",
        "category": "electronics",
        "price": "45",
        "security_deposit": "",
        "handover_methods": [
            "pickup"
        ],
        "description": "Extension board in good working condition, safe and useful for daily use.",
        "address": "pathanamthitta",
        "images": [
            "697e2df621a47_Extension lead (UK) 4 gang, 2 metre long cable!.jpg",
            "697e2df625191_Festive 4 Gang Extension Cable.jpg"
        ],
        "created_at": "2026-01-31 17:29:42",
        "status": "Pending Approval"
    },
    {
        "id": "item_697e2ecebfe2a",
        "user_id": "697e2d046713b",
        "owner_name": "Benta Biju",
        "title": "Trolley bag",
        "category": "outdoor-gear",
        "price": "150",
        "security_deposit": "",
        "handover_methods": [
            "pickup"
        ],
        "description": "Trolley bag for travel and storage use.",
        "address": "pathanamthitta",
        "images": [
            "697e2ecebc1e4_Suitcase.jpg",
            "697e2ecebefe1_download (17).jpg"
        ],
        "created_at": "2026-01-31 17:33:18",
        "status": "Pending Approval"
    },
    {
        "id": "item_697e305fd856c",
        "user_id": "697e2d046713b",
        "owner_name": "Benta Biju",
        "title": "Umbrella",
        "category": "outdoor-gear",
        "price": "20",
        "security_deposit": "",
        "handover_methods": [
            "pickup"
        ],
        "description": "Umbrella for daily use and travel",
        "address": "pathanamthitta",
        "images": [
            "697e305fd470c_Large 120 cm Wooden Handle Premium Umbrella - Navy.jpg",
            "697e305fd5967_Dark minimalist umbrella.jpg"
        ],
        "created_at": "2026-01-31 17:39:59",
        "status": "Pending Approval"
    },
    {
        "id": "item_697e31d9d9bdc",
        "user_id": "697e2d046713b",
        "owner_name": "Benta Biju",
        "title": "Study Table",
        "category": "student-essentials",
        "price": "170",
        "security_deposit": "",
        "handover_methods": [
            "delivery"
        ],
        "description": "Study table for reading, writing, and laptop use.",
        "address": "pathanamthitta",
        "images": [
            "697e31d9d3761_download (18).jpg",
            "697e31d9d6ca4_Desks You'll Love _ Wayfair.jpg"
        ],
        "created_at": "2026-01-31 17:46:17",
        "status": "Pending Approval"
    },
    {
        "id": "item_697e35c78c4c8",
        "user_id": "697e2d046713b",
        "owner_name": "Benta Biju",
        "title": "Thermometer",
        "category": "medical",
        "price": "30",
        "security_deposit": "",
        "handover_methods": [
            "pickup"
        ],
        "description": "Thermometer for checking body temperature, easy to use at home",
        "address": "pathanamthitta",
        "images": [
            "697e35c788714_Thermom\u00e8tre (1).jpg",
            "697e35c78b512_Thermom\u00e8tre.jpg"
        ],
        "created_at": "2026-01-31 18:03:03",
        "updated_at": "2026-01-31 18:03:03",
        "status": "Pending Approval"
    },
    {
        "id": "item_697e3639a5226",
        "user_id": "697e2d046713b",
        "owner_name": "Benta Biju",
        "title": "Walking stick",
        "category": "medical",
        "price": "80",
        "security_deposit": "",
        "handover_methods": [
            "pickup"
        ],
        "description": "Walking stick to help with balance and support while walking",
        "address": "pathanamthitta",
        "images": [
            "697e3639a2cfa_Made by rollatorshopping.jpg",
            "697e3639a416b_Wooden Walking Sticks Solid Wood Cane Old Man Walking Stick 92cm14cm Mobi.jpg"
        ],
        "created_at": "2026-01-31 18:04:57",
        "updated_at": "2026-01-31 18:04:57",
        "status": "Pending Approval"
    },
    {
        "id": "item_697e37215c616",
        "user_id": "697e2d046713b",
        "owner_name": "Benta Biju",
        "title": "Clothes rack",
        "category": "home-essentials",
        "price": "120",
        "security_deposit": "",
        "handover_methods": [
            "pickup"
        ],
        "description": "Clothes rack for hanging and organizing clothes at home or hostel.",
        "address": "pathanamthitta",
        "images": [
            "697e372159f1a_Egon Clothes Rack.jpg",
            "697e37215b35f_Home D\u00e9cor + Apartment Sale.jpg"
        ],
        "created_at": "2026-01-31 18:08:49",
        "updated_at": "2026-01-31 18:08:49",
        "status": "Pending Approval"
    },
    {
        "id": "item_697e38ae71c35",
        "user_id": "697e2d046713b",
        "owner_name": "Benta Biju",
        "title": "Mixer grinder",
        "category": "home-essentials",
        "price": "150",
        "security_deposit": "",
        "handover_methods": [
            "pickup"
        ],
        "description": "Mixer grinder for grinding, blending, and cooking needs at home.",
        "address": "pathanamthitta",
        "images": [
            "697e38ae6aabd_Buy Philips HL7756_01 Mixer Grinder 750 Watt.jpg",
            "697e38ae6ca9c_Buy Mixer Grinder Online for Kitchen with Up to 65% OFF on Amazon.jpg"
        ],
        "created_at": "2026-01-31 18:15:26",
        "updated_at": "2026-01-31 18:15:26",
        "status": "Pending Approval"
    },
    {
        "id": "item_698039a94bde2",
        "user_id": "697ad695ad641",
        "owner_name": "Krishnaveni",
        "title": "Desk lamp",
        "category": "student-essentials",
        "price": "60",
        "security_deposit": "",
        "handover_methods": [
            "pickup"
        ],
        "description": "A small study lamp for reading and night study. Easy to use and saves space.",
        "address": "kanjirappally",
        "images": [
            "698039a94356a_Seealle Touch Table Lamp for Bedroom,3-Way Dimmable Small Bedside Lamps for Night Stands,Black Desk Lamp for Kids Room, Office, Living Room, End Table - Amazon_com.jpg",
            "698039a947db5_Touch Bedside Lamp for Bedroom, 3-Way Dimmable Farmhouse Table Lamps for Nightstand with Fabric Shade, Desk Lamp for Kids Reading, Home Office, with AU Plug (1 Pack).jpg"
        ],
        "created_at": "2026-02-02 06:44:09",
        "updated_at": "2026-02-02 06:44:09",
        "status": "Pending Approval"
    }
]